pyflume/__init__.py
pyflume/auth.py
pyflume/constants.py
pyflume/data.py
pyflume/devices.py
pyflume/leak.py
pyflume/notifications.py
pyflume/usage.py
pyflume/utils.py
PyFlume-0.8.3.dist-info/LICENSE
PyFlume-0.8.3.dist-info/METADATA
PyFlume-0.8.3.dist-info/WHEEL
PyFlume-0.8.3.dist-info/top_level.txt
PyFlume-0.8.3.dist-info/RECORD
