Metadata-Version: 2.1
Name: PyFlume
Version: 0.8.3
Summary: Package to integrate with Flume Sensor
Home-page: https://github.com/ChrisMandich/PyFlume
Author: ChrisMandich
Author-email: Chris@Mandich.net
Classifier: Programming Language :: Python :: 3
Classifier: License :: OSI Approved :: MIT License
Classifier: Operating System :: OS Independent
License-File: LICENSE
Requires-Dist: pyjwt
Requires-Dist: ratelimit
Requires-Dist: requests
Requires-Dist: backports.zoneinfo ; python_version < "3.9"
